PolyDeDupe/__init__.py
PolyDeDupe/non_alpha.py
PolyDeDupe/polydedupe.py
PolyDeDupe/py.typed
PolyDeDupe/version.py
PolyDeDupe-0.16.0.dist-info/LICENSE
PolyDeDupe-0.16.0.dist-info/METADATA
PolyDeDupe-0.16.0.dist-info/WHEEL
PolyDeDupe-0.16.0.dist-info/top_level.txt
PolyDeDupe-0.16.0.dist-info/RECORD
