Metadata-Version: 2.1
Name: PolyDeDupe
Version: 0.16.0
Author-email: Gagan Bhatia <gbhatia880@gmail.com>
License: Apache License
Project-URL: Homepage, https://github.com/gagan3012/PolyDeDupe
Project-URL: Repository, https://github.com/gagan3012/PolyDeDupe
Project-URL: Changelog, https://github.com/gagan3012/PolyDeDupe/blob/main/CHANGELOG.md
Classifier: Intended Audience :: Science/Research
Classifier: Development Status :: 3 - Alpha
Classifier: License :: OSI Approved :: Apache Software License
Classifier: Programming Language :: Python :: 3
Classifier: Topic :: Scientific/Engineering :: Artificial Intelligence
Requires-Python: >=3.8
License-File: LICENSE
Requires-Dist: datasets
Requires-Dist: datasketch
Requires-Dist: dpu-utils
Requires-Dist: transformers
Requires-Dist: regex
Requires-Dist: scikit-learn
Requires-Dist: sentence-transformers
Provides-Extra: dev
Requires-Dist: ruff ; extra == 'dev'
Requires-Dist: mypy <1.8,>=1.0 ; extra == 'dev'
Requires-Dist: black <24.0,>=23.0 ; extra == 'dev'
Requires-Dist: isort <5.13,>=5.12 ; extra == 'dev'
Requires-Dist: pytest ; extra == 'dev'
Requires-Dist: pytest-sphinx ; extra == 'dev'
Requires-Dist: pytest-cov ; extra == 'dev'
Requires-Dist: twine >=1.11.0 ; extra == 'dev'
Requires-Dist: build ; extra == 'dev'
Requires-Dist: setuptools ; extra == 'dev'
Requires-Dist: wheel ; extra == 'dev'
Requires-Dist: Sphinx ; extra == 'dev'
Requires-Dist: furo ==2023.9.10 ; extra == 'dev'
Requires-Dist: myst-parser <2.1,>=1.0 ; extra == 'dev'
Requires-Dist: sphinx-copybutton ==0.5.2 ; extra == 'dev'
Requires-Dist: sphinx-autobuild ==2021.3.14 ; extra == 'dev'
Requires-Dist: sphinx-autodoc-typehints ==1.25.2 ; extra == 'dev'
Requires-Dist: packaging ; extra == 'dev'
